{
  "workshops": [
    {
      "title": "Threading Workshop",
      "times": [
        {
          "datetime": "2016/05/21 13:00",
          "duration": null
        }
      ],
      "short": {
        "de": "Stricken lernen für Einsteiger.<br/>Es werden die Grundlagen des Strickens erläutert, sodass eigene Werke mit Nadel und Faden erschaffen werden können. Die traditionelle Art von Threads.<br/>Ob Maskottchen, Handysocken, Stulpen oder USB-Sticksocken, hier kann sich jeder ein pers&ouml;nliches Strickwerk erschaffen."
      },
      "language": ["de"],
      "author": "Lisa Wolf"
    }
  ]
}